uabnlputils/__init__.py
uabnlputils/textprocessor.py
uabnlputils-0.0.2.dist-info/METADATA
uabnlputils-0.0.2.dist-info/WHEEL
uabnlputils-0.0.2.dist-info/top_level.txt
uabnlputils-0.0.2.dist-info/RECORD
