Metadata-Version: 2.1
Name: uabnlputils
Version: 0.0.2
Summary: nlp utils
Author-email: Jerrison Chang-Sundin <cchang5@albany.edu>
Project-URL: Homepage, https://github.com/JerrisonChang/nlphelper
Project-URL: Bug Tracker, https://github.com/JerrisonChang/nlphelper/issues
Classifier: Programming Language :: Python :: 3
Classifier: License :: OSI Approved :: MIT License
Classifier: Operating System :: OS Independent
Requires-Python: >=3.8
Requires-Dist: spacy
Requires-Dist: pytextrank
